.gitignore
.pylintrc
.readthedocs.yml
CODE_OF_CONDUCT.md
LICENSE
README.rst
adafruit_extended_bus.py
requirements.txt
setup.py
.github/workflows/build.yml
.github/workflows/release.yml
adafruit_extended_bus.egg-info/PKG-INFO
adafruit_extended_bus.egg-info/SOURCES.txt
adafruit_extended_bus.egg-info/dependency_links.txt
adafruit_extended_bus.egg-info/requires.txt
adafruit_extended_bus.egg-info/top_level.txt
docs/api.rst
docs/conf.py
docs/examples.rst
docs/index.rst
docs/_static/favicon.ico
examples/extended_bus_simpletest.py