Metadata-Version: 2.1
Name: adafruit-extended-bus
Version: 1.0.1
Summary: Helper Library for Blinka to allow creating I2C and SPI busio objects by passing in the Bus ID.
Home-page: https://github.com/adafruit/Adafruit_Python_Extended_Bus
Author: Adafruit Industries
Author-email: circuitpython@adafruit.com
License: MIT
Keywords: adafruit blinka circuitpython micropython extended_bus busio i2c spi extended bus python
Platform: UNKNOWN
Classifier: Development Status :: 3 - Alpha
Classifier: Intended Audience :: Developers
Classifier: Topic :: Software Development :: Libraries
Classifier: Topic :: System :: Hardware
Classifier: License :: OSI Approved :: MIT License
Classifier: Programming Language :: Python :: 3
Classifier: Programming Language :: Python :: 3.4
Classifier: Programming Language :: Python :: 3.5
